<?xml version="1.0" encoding="utf-8"?>
<Application>
  <Views Id="Views">
    <DetailView Id="ItemInquiry_DetailView">
      <Layout Id="Layout">
        <LayoutGroup Id="Main">
          <LayoutGroup Id="Autobbf64865-516a-4878-aac6-eee1a0c2219b">
            <LayoutItem Id="ViewSales" ViewItem="ViewSales" />
          </LayoutGroup>
        </LayoutGroup>
      </Layout>
    </DetailView>
  </Views>
  <ActionDesign Id="ActionDesign">
    <ActionToContainerMapping Id="ActionToContainerMapping">
      <ActionContainer Id="ListView">
        <ActionLink ActionId="CreateSalesOrder" Index="1" />
        <ActionLink ActionId="CancelSalesOrder" Index="2" />
      </ActionContainer>
    </ActionToContainerMapping>
  </ActionDesign>
</Application>